Metadata-Version: 2.4
Name: pycupra
Version: 0.2.12
Summary: A library to read and send vehicle data via Cupra/Seat portal using the same API calls as the MyCupra/MySeat mobile app.
License-Expression: Apache-2.0
Requires-Python: >=3.12
License-File: LICENSE
Requires-Dist: aiohttp
Requires-Dist: beautifulsoup4
Requires-Dist: cryptography
Requires-Dist: lxml
Requires-Dist: PyJWT
Requires-Dist: xmltodict
Requires-Dist: pandas
Requires-Dist: pillow
Requires-Dist: protobuf
Requires-Dist: http-ece
Requires-Dist: requests-oauthlib
Dynamic: license-file
